rdsaledelivery/EcsInterface.py
rdsaledelivery/__init__.py
rdsaledelivery/mainModel.py
rdsaledelivery/metadata.py
rdsaledelivery/operation.py
rdsaledelivery/utility.py
rdsaledelivery-1.2.7.dist-info/METADATA
rdsaledelivery-1.2.7.dist-info/WHEEL
rdsaledelivery-1.2.7.dist-info/top_level.txt
rdsaledelivery-1.2.7.dist-info/RECORD
